{"zWz3NMl2douFKpRCqjGLzA==":"mbr-1620x1080.jpg","4wM9wvBgXbMHxncKqmY3Ew==":"artistic-4k-wallpaper-2000x1125.jpg","klGPg+ezgMBWOvRrZNBQyA==":"untitled.001-1024x768.jpg","i6/Xoua6XTdTq+fGVHeGQg==":"synoptyx.002-911x301.jpg","oJaVt4efBmKQG2d0zZvQbg==":"mbr-1-1620x1080.jpg","WtHLZ7wt4vEX+U2NuPNslg==":"untitled.001-1-1024x768.jpg","69ccg7jDKMYt+R/kjADInw==":"information_technology_767x400-767x400.jpg","QPOvo5CURSN3/eVFqnD66g==":"mbr-2-1620x1080.jpg","N4o9zHmTcp/0a0wga+kydQ==":"giraffe-minimalist-wallpaper-orange-272x501.png","+UumK10iTFT9OpyXaczMig==":"image-673x850.jpg","3w2xrqyW9KqwpNXDTuzqVQ==":"im.001-960x540.jpg"}